{
  "type_description_msg": {
    "type_description": {
      "type_name": "custom_interfaces/srv/CalculateTriangleArea_Request",
      "fields": [
        {
          "name": "a",
          "type": {
            "type_id": 11,
            "capacity": 0,
            "string_capacity": 0,
            "nested_type_name": ""
          },
          "default_value": ""
        },
        {
          "name": "b",
          "type": {
            "type_id": 11,
            "capacity": 0,
            "string_capacity": 0,
            "nested_type_name": ""
          },
          "default_value": ""
        },
        {
          "name": "c",
          "type": {
            "type_id": 11,
            "capacity": 0,
            "string_capacity": 0,
            "nested_type_name": ""
          },
          "default_value": ""
        }
      ]
    },
    "referenced_type_descriptions": []
  },
  "type_hashes": [
    {
      "type_name": "custom_interfaces/srv/CalculateTriangleArea_Request",
      "hash_string": "RIHS01_cecd2217358f5ee80919275bd9dda53c3adcb8eb30d50d2ed9732d17b9764840"
    }
  ]
}